wagglemsg/__init__.py
pywagglemsg-0.4.0.dist-info/LICENSE
pywagglemsg-0.4.0.dist-info/METADATA
pywagglemsg-0.4.0.dist-info/WHEEL
pywagglemsg-0.4.0.dist-info/top_level.txt
pywagglemsg-0.4.0.dist-info/RECORD
