Metadata-Version: 2.1
Name: pywagglemsg
Version: 0.4.0
Summary: Official Waggle Python message module.
Home-page: https://github.com/waggle-sensor/pywagglemsg
Author: Sean Shahkarami
Author-email: sean.shahkarami@gmail.com
Project-URL: Bug Tracker, https://github.com/waggle-sensor/pywagglemsg/issues
Classifier: Programming Language :: Python :: 3
Classifier: License :: OSI Approved :: BSD License
Classifier: Intended Audience :: Developers
Classifier: Operating System :: OS Independent
License-File: LICENSE
